adp_model_evaluation/__init__.py
adp_model_evaluation/adding_problem_model_evaluation.py
adp_model_evaluation-0.1.dist-info/LICENSE
adp_model_evaluation-0.1.dist-info/METADATA
adp_model_evaluation-0.1.dist-info/WHEEL
adp_model_evaluation-0.1.dist-info/top_level.txt
adp_model_evaluation-0.1.dist-info/RECORD
